LICENSE
MANIFEST.in
README.md
setup.py
bin/pygenerator
pygenerator/__init__.py
pygenerator/changes_content.py
pygenerator/contributing_content.py
pygenerator/license_content.py
pygenerator/manifest_content.py
pygenerator/project.py
pygenerator/readme_content.py
pygenerator/script_content.py
pygenerator/setup_content.py
pygenerator/test_content.py
pygenerator.egg-info/PKG-INFO
pygenerator.egg-info/SOURCES.txt
pygenerator.egg-info/dependency_links.txt
pygenerator.egg-info/not-zip-safe
pygenerator.egg-info/requires.txt
pygenerator.egg-info/top_level.txt
pygenerator/tests/__init__.py
pygenerator/tests/test_basic.py