Metadata-Version: 1.1
Name: pygenerator
Version: 0.0.2
Summary: Utilities to generate Python projects
Home-page: https://github.com/rgs1/pygenerator
Author: rgs
Author-email: rgs@itevenworks.net
License: apache
Platform: any
Classifier: Development Status :: 3 - Alpha
Classifier: License :: OSI Approved :: Apache Software License
Classifier: Programming Language :: Python
Classifier: Programming Language :: Python :: 2.7
